django_bpmn/__init__.py
django_bpmn/widget.py
django_bpmn/static/django_bpmn/css/bpmn-js.css
django_bpmn/static/django_bpmn/css/bpmn.css
django_bpmn/static/django_bpmn/css/diagram-js.css
django_bpmn/static/django_bpmn/css/django_bpmn.css
django_bpmn/static/django_bpmn/js/bpmn-modeler.development.js
django_bpmn/templates/django_bpmn/bpmn.html
django_bpmn-0.0.4.dist-info/LICENSE
django_bpmn-0.0.4.dist-info/METADATA
django_bpmn-0.0.4.dist-info/WHEEL
django_bpmn-0.0.4.dist-info/top_level.txt
django_bpmn-0.0.4.dist-info/RECORD
