Metadata-Version: 2.1
Name: django_bpmn
Version: 0.0.4
Summary: Encapsulates the bpmn-js diagram modeler into a Django widget
Home-page: https://github.com/jplobianco/django-bpmn
Author: Joao Paulo Lobianco
Author-email: joaopaulolobianco1@gmail.com
Project-URL: Bug Tracker, https://github.com/jplobianco/django-bpmn/issues
Keywords: bpmn,django
Classifier: Programming Language :: Python :: 3
Classifier: Framework :: Django
Classifier: Operating System :: OS Independent
Requires-Python: >=3.9
License-File: LICENSE
